CodeToCAD/CodeToCADInterface.py
CodeToCAD/CodeToCADProvider.py
CodeToCAD/TestCodeToCADProvider.py
CodeToCAD/__init__.py
CodeToCAD/utilities.py
CodeToCAD-0.2.1682497971.dist-info/LICENSE
CodeToCAD-0.2.1682497971.dist-info/METADATA
CodeToCAD-0.2.1682497971.dist-info/WHEEL
CodeToCAD-0.2.1682497971.dist-info/top_level.txt
CodeToCAD-0.2.1682497971.dist-info/RECORD
