Metadata-Version: 2.1
Name: CodeToCAD
Version: 0.2.1682497971
Summary: 3D modeling automation in your favorite modeling software.
Home-page: https://github.com/CodeToCAD/CodeToCAD
Author: CodeToCAD
Author-email: shehab@codethatdown.com
License: GPL v3
Classifier: Development Status :: 2 - Pre-Alpha
Classifier: License :: OSI Approved :: GNU General Public License v3 (GPLv3)
Classifier: Programming Language :: Python :: 3.10
Classifier: Programming Language :: Python :: 3.11
License-File: LICENSE
